{
  "term": "варшава",
  "moresuggestions": 10,
  "autoSuggestInstance": null,
  "trackingID": "8c1bc23c9a174fb5b0292231189b40a2",
  "misspellingfallback": false,
  "suggestions": [
    {
      "group": "CITY_GROUP",
      "entities": [
        {
          "geoId": "3765",
          "destinationId": "1036999",
          "landmarkCityDestinationId": null,
          "type": "CITY",
          "redirectPage": "DEFAULT_PAGE",
          "latitude": 52.23521,
          "longitude": 21.00887,
          "searchDetail": null,
          "caption": "<span class='highlighted'>Варшава</span>, Мазовецкое воеводство, Польша",
          "name": "Варшава"
        },
        {
          "geoId": "6057137",
          "destinationId": "1637670",
          "landmarkCityDestinationId": null,
          "type": "NEIGHBORHOOD",
          "redirectPage": "DEFAULT_PAGE",
          "latitude": 52.22830331103887,
          "longitude": 21.00932545622276,
          "searchDetail": null,
          "caption": "Центр, <span class='highlighted'>Варшава</span>, Мазовецкое воеводство, Польша",
          "name": "Центр"
        },
        {
          "geoId": "6057142",
          "destinationId": "10234424",
          "landmarkCityDestinationId": null,
          "type": "REGION",
          "redirectPage": "DEFAULT_PAGE",
          "latitude": 52.323173008216386,
          "longitude": 22.165943554832193,
          "searchDetail": null,
          "caption": "<span class='highlighted'>Варшава</span> – Восточная Польша, Польша",
          "name": "Варшава – Восточная Польша"
        },
        {
          "geoId": "6267017",
          "destinationId": "1770362",
          "landmarkCityDestinationId": null,
          "type": "NEIGHBORHOOD",
          "redirectPage": "DEFAULT_PAGE",
          "latitude": 52.19724337142564,
          "longitude": 21.1763359514784,
          "searchDetail": null,
          "caption": "Вавр, <span class='highlighted'>Варшава</span>, Мазовецкое воеводство, Польша",
          "name": "Вавр"
        }
      ]
    },
    {
      "group": "HOTEL_GROUP",
      "entities": [
        {
          "geoId": "19266",
          "destinationId": "128862",
          "landmarkCityDestinationId": null,
          "type": "HOTEL",
          "redirectPage": "DEFAULT_PAGE",
          "latitude": 52.23091,
          "longitude": 21.00139,
          "searchDetail": null,
          "caption": "Mercure Warszawa Centrum, <span class='highlighted'>Варшава</span>, Мазовецкое воеводство, Польша",
          "name": "Mercure Warszawa Centrum"
        },
        {
          "geoId": "3566",
          "destinationId": "248898",
          "landmarkCityDestinationId": null,
          "type": "HOTEL",
          "redirectPage": "DEFAULT_PAGE",
          "latitude": 52.2294,
          "longitude": 21.01344,
          "searchDetail": null,
          "caption": "Novotel Warszawa Centrum, <span class='highlighted'>Варшава</span>, Мазовецкое воеводство, Польша",
          "name": "Novotel Warszawa Centrum"
        },
        {
          "geoId": "26588891",
          "destinationId": "851844512",
          "landmarkCityDestinationId": null,
          "type": "HOTEL",
          "redirectPage": "DEFAULT_PAGE",
          "latitude": 52.2268,
          "longitude": 21.04138,
          "searchDetail": null,
          "caption": "ibis Styles Warszawa Centrum, <span class='highlighted'>Варшава</span>, Мазовецкое воеводство, Польша",
          "name": "ibis Styles Warszawa Centrum"
        },
        {
          "geoId": "7542922",
          "destinationId": "454318",
          "landmarkCityDestinationId": null,
          "type": "HOTEL",
          "redirectPage": "DEFAULT_PAGE",
          "latitude": 52.22535,
          "longitude": 21.00354,
          "searchDetail": null,
          "caption": "Hampton by Hilton Warsaw City Centre, <span class='highlighted'>Варшава</span>, Мазовецкое воеводство, Польша",
          "name": "Hampton by Hilton Warsaw City Centre"
        },
        {
          "geoId": "970855",
          "destinationId": "215962",
          "landmarkCityDestinationId": null,
          "type": "HOTEL",
          "redirectPage": "DEFAULT_PAGE",
          "latitude": 52.1708,
          "longitude": 20.97392,
          "searchDetail": null,
          "caption": "Courtyard by Marriott Warsaw Airport, <span class='highlighted'>Варшава</span>, Мазовецкое воеводство, Польша",
          "name": "Courtyard by Marriott Warsaw Airport"
        },
        {
          "geoId": "1075153",
          "destinationId": "217277",
          "landmarkCityDestinationId": null,
          "type": "HOTEL",
          "redirectPage": "DEFAULT_PAGE",
          "latitude": 52.2413,
          "longitude": 21.096177,
          "searchDetail": null,
          "caption": "Best Western Hotel Felix, <span class='highlighted'>Варшава</span>, Мазовецкое воеводство, Польша",
          "name": "Best Western Hotel Felix"
        }
      ]
    },
    {
      "group": "LANDMARK_GROUP",
      "entities": [
        {
          "geoId": "6331389",
          "destinationId": "1803150",
          "landmarkCityDestinationId": "1036999",
          "type": "LANDMARK",
          "redirectPage": "DEFAULT_PAGE",
          "latitude": 52.224718,
          "longitude": 21.023805,
          "searchDetail": null,
          "caption": "Посольство США, <span class='highlighted'>Варшава</span>, Мазовецкое воеводство, Польша",
          "name": "Посольство США"
        }
      ]
    },
    {
      "group": "TRANSPORT_GROUP",
      "entities": [
        {
          "geoId": "5718359",
          "destinationId": "1637027",
          "landmarkCityDestinationId": null,
          "type": "AIRPORT",
          "redirectPage": "DEFAULT_PAGE",
          "latitude": 52.170952,
          "longitude": 20.967527,
          "searchDetail": null,
          "caption": "<span class='highlighted'>Варшава</span>, Польша (WAW-Фредерик Шопен)",
          "name": "Варшава (WAW-Фредерик Шопен)"
        },
        {
          "geoId": "6177253",
          "destinationId": "1725812",
          "landmarkCityDestinationId": null,
          "type": "AIRPORT",
          "redirectPage": "DEFAULT_PAGE",
          "latitude": 52.445226,
          "longitude": 20.655293,
          "searchDetail": null,
          "caption": "Модлин, Польша (WMI-<span class='highlighted'>Варшава</span>-Модлин, Мазовия)",
          "name": "Модлин (WMI-Варшава-Модлин, Мазовия)"
        },
        {
          "geoId": "6022760",
          "destinationId": "1709015",
          "landmarkCityDestinationId": null,
          "type": "TRAIN_STATION",
          "redirectPage": "DEFAULT_PAGE",
          "latitude": 52.228288,
          "longitude": 21.003603,
          "searchDetail": null,
          "caption": "Центральный вокзал Варшавы, <span class='highlighted'>Варшава</span>, Мазовецкое воеводство, Польша",
          "name": "Центральный вокзал Варшавы"
        },
        {
          "geoId": "6045361",
          "destinationId": "1708994",
          "landmarkCityDestinationId": null,
          "type": "TRAIN_STATION",
          "redirectPage": "DEFAULT_PAGE",
          "latitude": 52.219511,
          "longitude": 20.965501,
          "searchDetail": null,
          "caption": "Станция Warszawa Zachodnia, <span class='highlighted'>Варшава</span>, Мазовецкое воеводство, Польша",
          "name": "Станция Warszawa Zachodnia"
        }
      ]
    }
  ],
  "geocodeFallback": false
}